MDANSE_GUI/ElementsDatabaseEditor.py
MDANSE_GUI/PeriodicTableViewer.py
MDANSE_GUI/Resources.py
MDANSE_GUI/TabbedWindow.py
MDANSE_GUI/UnitsEditor.py
MDANSE_GUI/UserSettingsEditor.py
MDANSE_GUI/__init__.py
MDANSE_GUI/main.py
MDANSE_GUI/DataViewModel/ActionsHolder.py
MDANSE_GUI/DataViewModel/TrajectoryHolder.py
MDANSE_GUI/DataViewModel/__init__.py
MDANSE_GUI/Icons/MDANSE.ico
MDANSE_GUI/Icons/__init__.py
MDANSE_GUI/Icons/element.png
MDANSE_GUI/Icons/periodic_table.png
MDANSE_GUI/Icons/units.png
MDANSE_GUI/Icons/user_definitions.png
MDANSE_GUI/InputWidgets/AseInputFileWidget.py
MDANSE_GUI/InputWidgets/AtomMappingWidget.py
MDANSE_GUI/InputWidgets/AtomSelectionWidget.py
MDANSE_GUI/InputWidgets/AtomTransmutationWidget.py
MDANSE_GUI/InputWidgets/BackupWidget.py
MDANSE_GUI/InputWidgets/BooleanWidget.py
MDANSE_GUI/InputWidgets/CheckableComboBox.py
MDANSE_GUI/InputWidgets/ComboWidget.py
MDANSE_GUI/InputWidgets/CorrelationFramesWidget.py
MDANSE_GUI/InputWidgets/DerivativeOrderWidget.py
MDANSE_GUI/InputWidgets/DistHistCutoffWidget.py
MDANSE_GUI/InputWidgets/DummyWidget.py
MDANSE_GUI/InputWidgets/FloatWidget.py
MDANSE_GUI/InputWidgets/FramesWidget.py
MDANSE_GUI/InputWidgets/HDFTrajectoryWidget.py
MDANSE_GUI/InputWidgets/InputDirectoryWidget.py
MDANSE_GUI/InputWidgets/InputFileWidget.py
MDANSE_GUI/InputWidgets/InstrumentResolutionWidget.py
MDANSE_GUI/InputWidgets/IntegerWidget.py
MDANSE_GUI/InputWidgets/InterpolationOrderWidget.py
MDANSE_GUI/InputWidgets/MDAnalysisCoordinateFileWidget.py
MDANSE_GUI/InputWidgets/MDAnalysisMDTrajTimeStepWidget.py
MDANSE_GUI/InputWidgets/MDAnalysisTopologyFileWidget.py
MDANSE_GUI/InputWidgets/MDTrajTopologyFileWidget.py
MDANSE_GUI/InputWidgets/MoleculeAndAxisWidget.py
MDANSE_GUI/InputWidgets/MoleculePreviewWidget.py
MDANSE_GUI/InputWidgets/MoleculeWidget.py
MDANSE_GUI/InputWidgets/MultiInputFileWidget.py
MDANSE_GUI/InputWidgets/MultipleCombosWidget.py
MDANSE_GUI/InputWidgets/OptionalFloatWidget.py
MDANSE_GUI/InputWidgets/OutputDirectoryWidget.py
mdanse_gui-1.0.0rc2.dist-info/licenses/AUTHORS
mdanse_gui-1.0.0rc2.dist-info/licenses/LICENSE
mdanse_gui-1.0.0rc2.dist-info/METADATA
mdanse_gui-1.0.0rc2.dist-info/WHEEL
mdanse_gui-1.0.0rc2.dist-info/entry_points.txt
mdanse_gui-1.0.0rc2.dist-info/top_level.txt
mdanse_gui-1.0.0rc2.dist-info/RECORD
