Metadata-Version: 2.4
Name: MDANSE_GUI
Version: 1.0.0rc2
Summary: MDANSE GUI package - the graphical interface for MDANSE
Maintainer-email: Maciej Bartkowiak <maciej.bartkowiak@stfc.ac.uk>, "Chi Y. Cheng" <chi.cheng@stfc.ac.uk>, Jacob Wilkins <jacob.wilkins@stfc.ac.uk>
License: GNU GENERAL PUBLIC LICENSE
Project-URL: homepage, https://www.isis.stfc.ac.uk/Pages/MDANSEproject.aspx
Project-URL: documentation, https://mdanse.readthedocs.io/en/protos/
Project-URL: repository, https://github.com/ISISNeutronMuon/MDANSE
Keywords: molecular dynamics,science,simulation,analysis
Classifier: Development Status :: 4 - Beta
Classifier: Intended Audience :: Science/Research
Classifier: Topic :: Scientific/Engineering :: Chemistry
Classifier: Topic :: Scientific/Engineering :: Physics
Classifier: Topic :: Scientific/Engineering :: Visualization
Classifier: Programming Language :: Python :: 3
Classifier: Programming Language :: Python :: 3.9
Classifier: Programming Language :: Python :: 3 :: Only
Classifier: License :: OSI Approved :: GNU General Public License v3 or later (GPLv3+)
Classifier: Operating System :: OS Independent
Requires-Python: >=3.9
License-File: LICENSE
License-File: AUTHORS
Requires-Dist: MDANSE
Requires-Dist: matplotlib
Requires-Dist: qtpy
Requires-Dist: vtk
Requires-Dist: PyQt6<=6.7.0
Requires-Dist: PyYAML
Requires-Dist: tomlkit
Dynamic: license-file
